proste_ai/__init__.py
proste_ai/ai.py
proste_ai/dane.py
proste_ai2-0.1.3.dist-info/LICENSE.txt
proste_ai2-0.1.3.dist-info/METADATA
proste_ai2-0.1.3.dist-info/WHEEL
proste_ai2-0.1.3.dist-info/top_level.txt
proste_ai2-0.1.3.dist-info/RECORD
