Metadata-Version: 2.1
Name: proste_ai2
Version: 0.1.3
Summary: Prosty pakiet AI do nauki
Author: Situus
Author-email: situs1235@gmail.com
License: MIT
Classifier: Programming Language :: Python :: 3
Classifier: License :: OSI Approved :: MIT License
Classifier: Operating System :: OS Independent
Requires-Python: >=3.7
License-File: LICENSE.txt
Requires-Dist: scikit-learn>=1.0
